[
    {
        "id": "862efbf94a18ea18849fbc48b4599327",
        "added_by": "mckraqs",
        "date": "06-03-2019",
        "task_id": "classification_Survival_status",
        "dataset_id": "openml_haberman",
        "parameters": {
            "algorithm": "auto",
            "leaf_size": 30,
            "metric": "minkowski",
            "metric_params": null,
            "n_jobs": null,
            "n_neighbors": 29,
            "p": 2,
            "weights": "uniform"
        },
        "preprocessing": {
            "Age_of_patient_at_time_of_operation": {
                "name": "Age_of_patient_at_time_of_operation",
                "type": "numerical",
                "number_of_unique_values": 49,
                "number_of_missing_values": 0,
                "cat_frequencies": null,
                "num_minimum": 30.0,
                "num_1qu": 45.0,
                "num_median": 53.0,
                "num_3q": 61.0,
                "num_maximum": 83.0
            },
            "Patients_year_of_operation": {
                "name": "Patients_year_of_operation",
                "type": "categorical",
                "number_of_unique_values": 12,
                "number_of_missing_values": 0,
                "cat_frequencies": {
                    "0.0": 31,
                    "1.0": 21,
                    "2.0": 25,
                    "3.0": 23,
                    "4.0": 21,
                    "5.0": 26,
                    "6.0": 29,
                    "7.0": 20,
                    "8.0": 24,
                    "9.0": 20,
                    "10.0": 12,
                    "11.0": 8
                },
                "num_minimum": null,
                "num_1qu": null,
                "num_median": null,
                "num_mean": null,
                "num_3qu": null,
                "num_maximum": null
            },
            "Number_of_positive_axillary_nodes_detected": {
                "name": "Number_of_positive_axillary_nodes_detected",
                "type": "numerical",
                "number_of_unique_values": 29,
                "number_of_missing_values": 0,
                "cat_frequencies": null,
                "num_minimum": 0.0,
                "num_1qu": 0.0,
                "num_median": 1.0,
                "num_3q": 4.0,
                "num_maximum": 52.0
            }
        }
    }
]