[
  {
    "id": "openml_confidence",
    "added_by": "MatiFilozof",
    "date": "08-06-2019",
    "name": "confidence",
    "source": "openml",
    "url": "https://www.openml.org/data/v1/download/53549/confidence.arff",
    "number_of_features": 4,
    "number_of_instances": 72,
    "number_of_missing_values": 0,
    "number_of_instances_with_missing_values": 0,
    "variables": {
      "P": {
        "name": "P",
        "type": "numerical",
        "number_of_unique_values": 67,
        "number_of_missing_values": 0,
        "cat_frequencies": null,
        "num_minimum": 50.4,
        "num_1qu": 89.2,
        "num_median": 309.95,
        "num_mean": 338.5736,
        "num_3qu": 474.225,
        "num_maximum": 1051.6
      },
      "N": {
        "name": "N",
        "type": "numerical",
        "number_of_unique_values": 67,
        "number_of_missing_values": 0,
        "cat_frequencies": null,
        "num_minimum": 120.2,
        "num_1qu": 209.05,
        "num_median": 1067.4,
        "num_mean": 1184.4403,
        "num_3qu": 2171.025,
        "num_maximum": 2567
      },
      "O": {
        "name": "O",
        "type": "numerical",
        "number_of_unique_values": 70,
        "number_of_missing_values": 0,
        "cat_frequencies": null,
        "num_minimum": 45.9,
        "num_1qu": 150.3,
        "num_median": 359.2,
        "num_mean": 400.6403,
        "num_3qu": 620.125,
        "num_maximum": 899.1
      },
      "binaryClass": {
        "name": "binaryClass",
        "type": "categorical",
        "number_of_unique_values": 2,
        "number_of_missing_values": 0,
        "cat_frequencies": {
          "P": 12,
          "N": 60
        },
        "num_minimum": null,
        "num_1qu": null,
        "num_median": null,
        "num_mean": null,
        "num_3qu": null,
        "num_maximum": null
      }
    }
  }
]
