[
  {
    "id": "6757aab11d448a63e3aa48195851e938",
    "added_by": "MatiFilozof",
    "date": "08-06-2019",
    "library": "mlr",
    "model_name": "classif.logreg",
    "task_id": "classification_binaryClass",
    "dataset_id": "openml_chscase_geyser1",
    "parameters": {
      "model": false
    },
    "preprocessing": {
      "col_1": {
        "name": "col_1",
        "type": "numerical",
        "number_of_unique_values": 16,
        "number_of_missing_values": 0,
        "cat_frequencies": null,
        "num_minimum": 1,
        "num_1qu": 5,
        "num_median": 16,
        "num_mean": 12.2973,
        "num_3qu": 20,
        "num_maximum": 23
      },
      "col_2": {
        "name": "col_2",
        "type": "numerical",
        "number_of_unique_values": 34,
        "number_of_missing_values": 0,
        "cat_frequencies": null,
        "num_minimum": 1.7,
        "num_1qu": 2.3,
        "num_median": 4,
        "num_mean": 3.5761,
        "num_3qu": 4.4,
        "num_maximum": 5.2
      },
      "binaryClass": {
        "name": "binaryClass",
        "type": "categorical",
        "number_of_unique_values": 2,
        "number_of_missing_values": 0,
        "cat_frequencies": {
          "P": 88,
          "N": 134
        },
        "num_minimum": null,
        "num_1qu": null,
        "num_median": null,
        "num_mean": null,
        "num_3qu": null,
        "num_maximum": null
      }
    }
  }
]
