[
  {
    "id": "3149aa5f3bd7e5e8bc617c5b40a1ff85",
    "added_by": "MatiFilozof",
    "date": "09-06-2019",
    "library": "mlr",
    "model_name": "classif.C50",
    "task_id": "classification_isPresent",
    "dataset_id": "openml_conference_attendance",
    "parameters": {
      "trials": 1,
      "rules": false,
      "subset": false,
      "bands": null,
      "winnow": false,
      "noGlobalPruning": false,
      "CF": 0.25,
      "minCases": 2,
      "fuzzyThreshold": false,
      "sample": 0,
      "seed": null,
      "earlyStopping": true,
      "label": "outcome"
    },
    "preprocessing": {
      "uni": {
        "name": "uni",
        "type": "categorical",
        "number_of_unique_values": 7,
        "number_of_missing_values": 0,
        "cat_frequencies": {
          "Gdansk": 10,
          "Krakow": 38,
          "Other": 31,
          "Poznan": 8,
          "Torun": 5,
          "Warszawa": 119,
          "Wroclaw": 35
        },
        "num_minimum": null,
        "num_1qu": null,
        "num_median": null,
        "num_mean": null,
        "num_3qu": null,
        "num_maximum": null
      },
      "tshirtSize": {
        "name": "tshirtSize",
        "type": "categorical",
        "number_of_unique_values": 7,
        "number_of_missing_values": 2,
        "cat_frequencies": {
          "DontWant": 11,
          "NA": 0,
          "L": 51,
          "M": 111,
          "S": 42,
          "XL": 20,
          "XXL": 9,
          "NA's": 2
        },
        "num_minimum": null,
        "num_1qu": null,
        "num_median": null,
        "num_mean": null,
        "num_3qu": null,
        "num_maximum": null
      },
      "favSubject": {
        "name": "favSubject",
        "type": "categorical",
        "number_of_unique_values": 3,
        "number_of_missing_values": 0,
        "cat_frequencies": {
          "DataScience": 127,
          "MathInTechnics": 100,
          "Other": 19
        },
        "num_minimum": null,
        "num_1qu": null,
        "num_median": null,
        "num_mean": null,
        "num_3qu": null,
        "num_maximum": null
      },
      "isPresent": {
        "name": "isPresent",
        "type": "categorical",
        "number_of_unique_values": 2,
        "number_of_missing_values": 0,
        "cat_frequencies": {
          "1": 215,
          "0": 31
        },
        "num_minimum": null,
        "num_1qu": null,
        "num_median": null,
        "num_mean": null,
        "num_3qu": null,
        "num_maximum": null
      },
      "wegan": {
        "name": "wegan",
        "type": "categorical",
        "number_of_unique_values": 2,
        "number_of_missing_values": 0,
        "cat_frequencies": {
          "1": 42,
          "0": 204
        },
        "num_minimum": null,
        "num_1qu": null,
        "num_median": null,
        "num_mean": null,
        "num_3qu": null,
        "num_maximum": null
      },
      "participation": {
        "name": "participation",
        "type": "categorical",
        "number_of_unique_values": 2,
        "number_of_missing_values": 0,
        "cat_frequencies": {
          "1": 41,
          "0": 205
        },
        "num_minimum": null,
        "num_1qu": null,
        "num_median": null,
        "num_mean": null,
        "num_3qu": null,
        "num_maximum": null
      },
      "regDateCat": {
        "name": "regDateCat",
        "type": "categorical",
        "number_of_unique_values": 5,
        "number_of_missing_values": 0,
        "cat_frequencies": {
          "1": 50,
          "2": 30,
          "3": 51,
          "4": 30,
          "5": 85
        },
        "num_minimum": null,
        "num_1qu": null,
        "num_median": null,
        "num_mean": null,
        "num_3qu": null,
        "num_maximum": null
      }
    }
  }
]
