[
  {
    "id": "d5e139d411c2e0463ca86d69c48c9338",
    "added_by": "MatiFilozof",
    "date": "09-06-2019",
    "library": "mlr",
    "model_name": "classif.earth",
    "task_id": "classification_binaryClass",
    "dataset_id": "openml_fri_c1_100_10",
    "parameters": {
      "trace": 0,
      "keepxy": false,
      "degree": 1,
      "penalty": null,
      "nk": null,
      "thresh": 0.001,
      "minspan": 0,
      "endspan": 0,
      "newvar.penalty": 0,
      "fast.k": 20,
      "fast.beta": 1,
      "pmethod": "backward",
      "nprune": null,
      "ncross": 1,
      "nfold": 0,
      "stratify": true,
      "linpreds": false,
      "link": "logit",
      "maxit": 25,
      "allowed": null,
      "Adjust.endspan": 2,
      "Force.weights": false,
      "Use.beta.cache": true,
      "Force.xtx.prune": false,
      "Get.leverages": true,
      "Exhaustive.tol": 1e-010
    },
    "preprocessing": {
      "oz1": {
        "name": "oz1",
        "type": "numerical",
        "number_of_unique_values": 100,
        "number_of_missing_values": 0,
        "cat_frequencies": null,
        "num_minimum": -2.6067,
        "num_1qu": -0.7488,
        "num_median": 0.0554,
        "num_mean": -2e-008,
        "num_3qu": 0.8,
        "num_maximum": 2.2049
      },
      "oz2": {
        "name": "oz2",
        "type": "numerical",
        "number_of_unique_values": 100,
        "number_of_missing_values": 0,
        "cat_frequencies": null,
        "num_minimum": -2.0491,
        "num_1qu": -0.7991,
        "num_median": 0.205,
        "num_mean": -2e-008,
        "num_3qu": 0.6625,
        "num_maximum": 1.7154
      },
      "oz3": {
        "name": "oz3",
        "type": "numerical",
        "number_of_unique_values": 100,
        "number_of_missing_values": 0,
        "cat_frequencies": null,
        "num_minimum": -1.7251,
        "num_1qu": -0.8097,
        "num_median": -0.007,
        "num_mean": 3e-008,
        "num_3qu": 0.9087,
        "num_maximum": 1.6232
      },
      "oz4": {
        "name": "oz4",
        "type": "numerical",
        "number_of_unique_values": 100,
        "number_of_missing_values": 0,
        "cat_frequencies": null,
        "num_minimum": -1.6551,
        "num_1qu": -0.9529,
        "num_median": 0.0705,
        "num_mean": 1e-008,
        "num_3qu": 0.8126,
        "num_maximum": 1.6361
      },
      "oz5": {
        "name": "oz5",
        "type": "numerical",
        "number_of_unique_values": 100,
        "number_of_missing_values": 0,
        "cat_frequencies": null,
        "num_minimum": -1.6421,
        "num_1qu": -0.7702,
        "num_median": -0.0536,
        "num_mean": -8e-008,
        "num_3qu": 0.8702,
        "num_maximum": 1.7178
      },
      "oz6": {
        "name": "oz6",
        "type": "numerical",
        "number_of_unique_values": 100,
        "number_of_missing_values": 0,
        "cat_frequencies": null,
        "num_minimum": -1.8918,
        "num_1qu": -0.8297,
        "num_median": -0.0082,
        "num_mean": 2e-008,
        "num_3qu": 0.9199,
        "num_maximum": 1.6152
      },
      "oz7": {
        "name": "oz7",
        "type": "numerical",
        "number_of_unique_values": 100,
        "number_of_missing_values": 0,
        "cat_frequencies": null,
        "num_minimum": -1.606,
        "num_1qu": -0.8048,
        "num_median": -0.0928,
        "num_mean": 5.0524e-018,
        "num_3qu": 0.7568,
        "num_maximum": 1.854
      },
      "oz8": {
        "name": "oz8",
        "type": "numerical",
        "number_of_unique_values": 100,
        "number_of_missing_values": 0,
        "cat_frequencies": null,
        "num_minimum": -1.6593,
        "num_1qu": -0.8413,
        "num_median": -0.0172,
        "num_mean": 1e-008,
        "num_3qu": 0.9061,
        "num_maximum": 1.5594
      },
      "oz9": {
        "name": "oz9",
        "type": "numerical",
        "number_of_unique_values": 100,
        "number_of_missing_values": 0,
        "cat_frequencies": null,
        "num_minimum": -1.9351,
        "num_1qu": -0.8867,
        "num_median": 0.1746,
        "num_mean": -3e-008,
        "num_3qu": 0.7911,
        "num_maximum": 1.582
      },
      "oz10": {
        "name": "oz10",
        "type": "numerical",
        "number_of_unique_values": 100,
        "number_of_missing_values": 0,
        "cat_frequencies": null,
        "num_minimum": -1.6615,
        "num_1qu": -0.8646,
        "num_median": -0.0694,
        "num_mean": 3e-008,
        "num_3qu": 1.0069,
        "num_maximum": 1.5202
      },
      "binaryClass": {
        "name": "binaryClass",
        "type": "categorical",
        "number_of_unique_values": 2,
        "number_of_missing_values": 0,
        "cat_frequencies": {
          "P": 47,
          "N": 53
        },
        "num_minimum": null,
        "num_1qu": null,
        "num_median": null,
        "num_mean": null,
        "num_3qu": null,
        "num_maximum": null
      }
    }
  }
]
