[
  {
    "id": "d542b6b8229506b9e5130f14c2da229c",
    "added_by": "MatiFilozof",
    "date": "08-06-2019",
    "library": "mlr",
    "model_name": "classif.ctree",
    "task_id": "classification_Winner",
    "dataset_id": "openml_analcatdata_boxing1",
    "parameters": {
      "teststat": "quad",
      "testtype": "Bonferroni",
      "mincriterion": 0.95,
      "minsplit": 20,
      "minbucket": 7,
      "stump": false,
      "nresample": 9999,
      "maxsurrogate": 0,
      "mtry": 0,
      "savesplitstats": true,
      "maxdepth": 0
    },
    "preprocessing": {
      "Judge": {
        "name": "Judge",
        "type": "categorical",
        "number_of_unique_values": 10,
        "number_of_missing_values": 0,
        "cat_frequencies": {
          "Associated_Press": 12,
          "Boxing_Monthly-Leach": 12,
          "Boxing_Times": 12,
          "E._Williams": 12,
          "ESPN": 12,
          "HBO-Lederman": 12,
          "L._OConnell": 12,
          "S._Christodoulu": 12,
          "Sportsline": 12,
          "Sportsticker": 12
        },
        "num_minimum": null,
        "num_1qu": null,
        "num_median": null,
        "num_mean": null,
        "num_3qu": null,
        "num_maximum": null
      },
      "Official": {
        "name": "Official",
        "type": "categorical",
        "number_of_unique_values": 2,
        "number_of_missing_values": 0,
        "cat_frequencies": {
          "No": 84,
          "Yes": 36
        },
        "num_minimum": null,
        "num_1qu": null,
        "num_median": null,
        "num_mean": null,
        "num_3qu": null,
        "num_maximum": null
      },
      "Round": {
        "name": "Round",
        "type": "categorical",
        "number_of_unique_values": 12,
        "number_of_missing_values": 0,
        "cat_frequencies": {
          "1": 10,
          "2": 10,
          "3": 10,
          "4": 10,
          "5": 10,
          "6": 10,
          "7": 10,
          "8": 10,
          "9": 10,
          "10": 10,
          "11": 10,
          "12": 10
        },
        "num_minimum": null,
        "num_1qu": null,
        "num_median": null,
        "num_mean": null,
        "num_3qu": null,
        "num_maximum": null
      },
      "Winner": {
        "name": "Winner",
        "type": "categorical",
        "number_of_unique_values": 2,
        "number_of_missing_values": 0,
        "cat_frequencies": {
          "Holyfield": 42,
          "Lewis": 78
        },
        "num_minimum": null,
        "num_1qu": null,
        "num_median": null,
        "num_mean": null,
        "num_3qu": null,
        "num_maximum": null
      }
    }
  }
]
